README
screensaver.py
setup.py
slidesaver-daemon
slidesaver/__init__.py
slidesaver/util.py
slideshow_screensaver.egg-info/PKG-INFO
slideshow_screensaver.egg-info/SOURCES.txt
slideshow_screensaver.egg-info/dependency_links.txt
slideshow_screensaver.egg-info/requires.txt
slideshow_screensaver.egg-info/top_level.txt