Metadata-Version: 1.0
Name: slideshow-screensaver
Version: 0.2
Summary: Slideshow screensaver for GNU/Linux using OpenGL
Home-page: https://github.com/jamesadney/slideshow-screensaver
Author: James Adney
Author-email: jfadney@gmail.com
License: GPL3
Keywords: slideshow,screensaver,opengl
Platform: UNKNOWN
